printextent/__init__.py
printextent/asciiPrint.py
printextent/colorPrint.py
printextent/colorReturn.py
printextent/errorUserPrint.py
printextent/informUserPrint.py
printextent/listPrint.py
printextent/progressBarPrint.py
printextent/repeatInput.py
printextent/reversePrint.py
printextent/successUserPrint.py
printextent/typewritePrint.py
printextent/warnUserPrint.py
printextent-0.1.13.dist-info/METADATA
printextent-0.1.13.dist-info/WHEEL
printextent-0.1.13.dist-info/top_level.txt
printextent-0.1.13.dist-info/RECORD
