Metadata-Version: 2.1
Name: printextent
Version: 0.1.13
Summary: Printing made for the creativity.
Author: Thomas Kyrouac
Author-email: thomaskkyrouac@gmail.com
Classifier: Programming Language :: Python :: 3
Classifier: License :: OSI Approved :: MIT License
Classifier: Operating System :: OS Independent
Requires-Python: >=3.6
